img2pdfify/__main__.py
img2pdfify-0.2.5.dist-info/METADATA
img2pdfify-0.2.5.dist-info/WHEEL
img2pdfify-0.2.5.dist-info/entry_points.txt
img2pdfify-0.2.5.dist-info/top_level.txt
img2pdfify-0.2.5.dist-info/RECORD
