Metadata-Version: 2.4
Name: img2pdfify
Version: 0.2.5
Summary: Convert images to a single PDF via command line
Author: Sharan Thakur
Requires-Python: >=3.7
Requires-Dist: Pillow
